conftest.py
test_benchmark.py
timeseriesflattener/__init__.py
timeseriesflattener/aggregators.py
timeseriesflattener/aggregators_test.py
timeseriesflattener/intermediary.py
timeseriesflattener/main.py
timeseriesflattener/main_test.py
timeseriesflattener/py.typed
timeseriesflattener/utils.py
timeseriesflattener/validators.py
timeseriesflattener/processors/__init__.py
timeseriesflattener/processors/static.py
timeseriesflattener/processors/static_test.py
timeseriesflattener/processors/temporal.py
timeseriesflattener/processors/temporal_test.py
timeseriesflattener/processors/timedelta.py
timeseriesflattener/specs/__init__.py
timeseriesflattener/specs/from_legacy.py
timeseriesflattener/specs/outcome.py
timeseriesflattener/specs/prediction_times.py
timeseriesflattener/specs/static.py
timeseriesflattener/specs/temporal.py
timeseriesflattener/specs/test_from_legacy.py
timeseriesflattener/specs/test_specs.py
timeseriesflattener/specs/timedelta.py
timeseriesflattener/specs/timestamp.py
timeseriesflattener/specs/value.py
timeseriesflattener/testing/load_synth_data.py
timeseriesflattener/testing/utils_for_testing.py
timeseriesflattener/testing/synth_data_generator/__init__.py
timeseriesflattener/testing/synth_data_generator/synth_col_generators.py
timeseriesflattener/testing/synth_data_generator/synth_prediction_times_generator.py
timeseriesflattener/testing/synth_data_generator/synth_txt_data_generator.py
timeseriesflattener/testing/synth_data_generator/utils.py
timeseriesflattener/testing/test_data/flattened/generated_with_outcome/create_synth_flattened_with_outcome.py
timeseriesflattener/testing/test_data/flattened/generated_with_outcome/synth_flattened_with_outcome.csv
timeseriesflattener/testing/test_data/raw/create_synth_birthdays.py
timeseriesflattener/testing/test_data/raw/create_synth_prediction_times.py
timeseriesflattener/testing/test_data/raw/create_synth_raw_binary.py
timeseriesflattener/testing/test_data/raw/create_synth_raw_float.py
timeseriesflattener-2.5.2.dist-info/licenses/LICENSE
timeseriesflattener-2.5.2.dist-info/METADATA
timeseriesflattener-2.5.2.dist-info/WHEEL
timeseriesflattener-2.5.2.dist-info/top_level.txt
timeseriesflattener-2.5.2.dist-info/RECORD
