Metadata-Version: 2.4
Name: timeseriesflattener
Version: 2.5.2
Summary: A package for converting time series data from e.g. electronic health records into wide format data.
Author: Kenneth Enevoldsen
Author-email: Lasse Hansen <lasseh0310@gmail.com>, Jakob Grøhn Damgaard <bokajgd@gmail.com>, Martin Bernstorff <martinbernstorff@gmail.com>
License: MIT License
Project-URL: homepage, https://github.com/Aarhus-Psychiatry-Research/timeseriesflattener
Project-URL: repository, https://github.com/Aarhus-Psychiatry-Research/timeseriesflattener
Project-URL: documentation, https://aarhus-psychiatry-research.github.io/timeseriesflattener/
Classifier: Operating System :: POSIX :: Linux
Classifier: Operating System :: MacOS :: MacOS X
Classifier: Operating System :: Microsoft :: Windows
Classifier: Programming Language :: Python :: 3.8
Classifier: Programming Language :: Python :: 3.9
Classifier: Programming Language :: Python :: 3.10
Classifier: Programming Language :: Python :: 3.11
Requires-Python: <3.13.0,>=3.9.0
License-File: LICENSE
Requires-Dist: scipy>=1.8.0
Requires-Dist: scikit-learn>=1.1.2
Requires-Dist: pydantic>=2.0.0
Requires-Dist: pandas>=1.4.0
Requires-Dist: catalogue>=2.0.0
Requires-Dist: numpy>=1.23.3
Requires-Dist: pyarrow>=8.0.0
Requires-Dist: protobuf>=4.25.8
Requires-Dist: frozendict>=2.3.4
Requires-Dist: coloredlogs>14.0.0
Requires-Dist: tqdm>4.1.0
Requires-Dist: polars>=0.19.0
Requires-Dist: iterpy==1.6.0
Requires-Dist: rich>=13.0.0
Requires-Dist: ipykernel[docs]>=6.29.5
Provides-Extra: dev
Requires-Dist: pyright==1.1.330.post0; extra == "dev"
Requires-Dist: pre-commit==3.4.0; extra == "dev"
Requires-Dist: ruff==0.2.1; extra == "dev"
Requires-Dist: pandas-stubs==2.2.0.240218; extra == "dev"
Requires-Dist: invoke==2.1.1; extra == "dev"
Provides-Extra: test
Requires-Dist: pytest==7.2.2; extra == "test"
Requires-Dist: pytest-cov==3.0.0; extra == "test"
Requires-Dist: pytest-xdist==3.1.0; extra == "test"
Requires-Dist: pytest-sugar==0.9.7; extra == "test"
Requires-Dist: pytest-testmon==2.1.0; extra == "test"
Requires-Dist: pytest-benchmark==4.0.0; extra == "test"
Requires-Dist: pytest-codspeed==2.2.0; extra == "test"
Provides-Extra: docs
Requires-Dist: sphinx==5.3.0; extra == "docs"
Requires-Dist: furo==2023.3.27; extra == "docs"
Requires-Dist: sphinx-copybutton==0.5.2; extra == "docs"
Requires-Dist: sphinxext-opengraph==0.8.2; extra == "docs"
Requires-Dist: myst-nb==0.17.2; extra == "docs"
Requires-Dist: sphinx_design==0.3.0; extra == "docs"
Requires-Dist: ipykernel>=6.29.5; extra == "docs"
Provides-Extra: tutorials
Requires-Dist: jupyter<1.1.0,>=1.0.0; extra == "tutorials"
Requires-Dist: skimpy==0.0.15; extra == "tutorials"
Dynamic: license-file
